bluetooth/__init__.py
bluetooth/_msbt.cp311-win_amd64.pyd
bluetooth/ble.py
bluetooth/bluez.py
bluetooth/btcommon.py
bluetooth/macos.py
bluetooth/msbt.py
pybluez_edge-2022.12.6.dist-info/COPYING
pybluez_edge-2022.12.6.dist-info/METADATA
pybluez_edge-2022.12.6.dist-info/WHEEL
pybluez_edge-2022.12.6.dist-info/eager_resources.txt
pybluez_edge-2022.12.6.dist-info/top_level.txt
pybluez_edge-2022.12.6.dist-info/zip-safe
pybluez_edge-2022.12.6.dist-info/RECORD
